Workbook

Sheet Instrucoes
B1: ANÁLISE FINANCEIRA COM IA — Planilha de Apoio
B2: Curso de Capacitação em IA · Exercício de Análise de Dados
B4: COMO USAR
B5: 1. Abra a aba "Lancamentos": é a base de dados (receitas e despesas de Jan–Mar/2026).
B6: 2. Faça upload deste arquivo na ferramenta de IA OU copie e cole os dados da aba "Lancamentos".
B7: 3. Cole o prompt abaixo, preenchendo os campos entre colchetes.
B8: 4. Compare a resposta da IA com a aba "Gabarito (Instrutor)" — ela lista o que foi plantado nos dados.
B10: DADOS DE CONTEXTO (para preencher no prompt)
B11: Período analisado: JAN–MAR 2026
B12: Tipo de negócio: VAREJO (loja física + e-commerce)
B13: Faturamento médio mensal: ~ R$ 254.667 (Jan 268k · Fev 255k · Mar 241k)
B15: PROMPT (copie e cole)
B16: Você é um analista financeiro sênior especializado em gestão de custos e auditoria interna. Analise os dados financeiros abaixo e entregue um relatório executivo: Período analisado: [JAN–MAR 2026] Tipo de negócio: [VAREJO] Faturamento médio mensal: [~R$ 254.000] Por favor, analise e entregue: 1. VISÃO GERAL — resumo financeiro em 5 linhas 2. TOP 5 DESPESAS — maiores gastos com % do total 3. ANOMALIAS — valores fora do padrão, duplicatas, picos inexplicados 4. TENDÊNCIAS — o que está crescendo ou diminuindo ao longo do período 5. ALERTAS CRÍTICOS — qualquer sinal de problema financeiro 6. OPORTUNIDADES — onde posso reduzir custos sem prejudicar a operação 7. RECOMENDAÇÕES — 3 ações práticas para os próximos 30 dias --- DADOS: [COLE OS DADOS DA ABA "Lancamentos" OU INFORME QUE FEZ UPLOAD DO ARQUIVO]

Sheet Lancamentos
A1: Data | B1: Mês | C1: Tipo | D1: Categoria | E1: Descrição / Fornecedor | F1: Documento | G1: Forma de Pagamento | H1: Valor (R$)
A2: 46024 | B2: Jan/2026 | C2: Despesa | D2: Software e Assinaturas | E2: ERP / gestão | F2: SW-011 | G2: Cartão corporativo | H2: 890
A3: 46024 | B3: Jan/2026 | C3: Despesa | D3: Software e Assinaturas | E3: Suite de produtividade | F3: SW-012 | G3: Cartão corporativo | H3: 350
A4: 46025 | B4: Jan/2026 | C4: Despesa | D4: Despesas Bancárias | E4: Tarifas de conta | F4: BC-011 | G4: Débito | H4: 480
A5: 46026 | B5: Jan/2026 | C5: Despesa | D5: Mercadorias para Revenda (CMV) | E5: Beta Atacado S.A. | F5: NF 84830 | G5: Boleto | H5: 27803.28
A6: 46027 | B6: Jan/2026 | C6: Receita | D6: Vendas - Loja Física | E6: Recebimento Loja Física - semana 1 | F6: REC-0101 | G6: Cartão/PIX | H6: 45929.34
A7: 46027 | B7: Jan/2026 | C7: Receita | D7: Vendas - E-commerce | E7: Recebimento E-commerce - semana 1 | F7: REC-0101 | G7: Gateway online | H7: 31050.65
A8: 46027 | B8: Jan/2026 | C8: Despesa | D8: Folha de Pagamento | E8: Folha 1ª quinzena | F8: FP-011 | G8: Transferência | H8: 18178.58
A9: 46029 | B9: Jan/2026 | C9: Despesa | D9: Encargos Sociais (INSS/FGTS) | E9: Encargos Sociais (INSS/FGTS) | F9: ENC-01 | G9: Transferência | H9: 12200
A10: 46029 | B10: Jan/2026 | C10: Despesa | D10: Aluguel | E10: Aluguel | F10: ALU-01 | G10: Transferência | H10: 18000
A11: 46029 | B11: Jan/2026 | C11: Despesa | D11: Telefone e Internet | E11: Telefone e Internet | F11: TEL-01 | G11: Transferência | H11: 1450
A12: 46029 | B12: Jan/2026 | C12: Despesa | D12: Manutenção e Reparos | E12: Manutenção e Reparos | F12: MAN-01 | G12: Transferência | H12: 1900
A13: 46029 | B13: Jan/2026 | C13: Despesa | D13: Contabilidade | E13: Contabilidade | F13: CON-01 | G13: Transferência | H13: 2800
... A104: 46109 | B104: Mar/2026 | C104: Despesa | D104: Taxas de Cartão/Maquininha | E104: Taxa adquirente (débito) | F104: TX-032 | G104: Desconto | H104: 3267.11
G106: Total Receitas | H106: =SUMIF(C2:C104,"Receita",H2:H104) -> 764000
G107: Total Despesas | H107: =SUMIF(C2:C104,"Despesa",H2:H104) -> 828270
G108: Resultado | H108: =H106-H107 -> -64270

Sheet Resumo
A1: RESUMO MENSAL — JAN a MAR/2026
A3: Categoria | B3: Jan/2026 | C3: Fev/2026 | D3: Mar/2026 | E3: Total Tri. | F3: % do Total
A4: RECEITAS
A5: Vendas - Loja Física | B5: =SUMIFS(Lancamentos!$H$2:$H$104,Lancamentos!$B$2:$B$104,"Jan/2026",Lancamentos!$D$2:$D$104,"Vendas - Loja Física") -> 182000 | C5: =SUMIFS(Lancamentos!$H$2:$H$104,Lancamentos!$B$2:$B$104,"Fev/2026",Lancamentos!$D$2:$D$104,"Vendas - Loja Física") -> 170000 | D5: =SUMIFS(Lancamentos!$H$2:$H$104,Lancamentos!$B$2:$B$104,"Mar/2026",Lancamentos!$D$2:$D$104,"Vendas - Loja Física") -> 158000 | E5: =SUM(B5:D5) -> 510000
A6: Vendas - E-commerce | B6: =SUMIFS(Lancamentos!$H$2:$H$104,Lancamentos!$B$2:$B$104,"Jan/2026",Lancamentos!$D$2:$D$104,"Vendas - E-commerce") -> 86000 | C6: =SUMIFS(Lancamentos!$H$2:$H$104,Lancamentos!$B$2:$B$104,"Fev/2026",Lancamentos!$D$2:$D$104,"Vendas - E-commerce") -> 85000 | D6: =SUMIFS(Lancamentos!$H$2:$H$104,Lancamentos!$B$2:$B$104,"Mar/2026",Lancamentos!$D$2:$D$104,"Vendas - E-commerce") -> 83000 | E6: =SUM(B6:D6) -> 254000
A7: Total Receitas | B7: =SUM(B5:B6) -> 268000 | C7: =SUM(C5:C6) -> 255000 | D7: =SUM(D5:D6) -> 241000 | E7: =SUM(E5:E6) -> 764000
A9: DESPESAS
A10: Aluguel | B10: =SUMIFS(Lancamentos!$H$2:$H$104,Lancamentos!$B$2:$B$104,"Jan/2026",Lancamentos!$D$2:$D$104,"Aluguel") -> 18000 | C10: =SUMIFS(Lancamentos!$H$2:$H$104,Lancamentos!$B$2:$B$104,"Fev/2026",Lancamentos!$D$2:$D$104,"Aluguel") -> 18000 | D10: =SUMIFS(Lancamentos!$H$2:$H$104,Lancamentos!$B$2:$B$104,"Mar/2026",Lancamentos!$D$2:$D$104,"Aluguel") -> 18000 | E10: =SUM(B10:D10) -> 54000 | F10: =E10/$E$30 -> 0.065196132
A11: Consultoria | B11: =SUMIFS(Lancamentos!$H$2:$H$104,Lancamentos!$B$2:$B$104,"Jan/2026",Lancamentos!$D$2:$D$104,"Consultoria") -> 0 | C11: =SUMIFS(Lancamentos!$H$2:$H$104,Lancamentos!$B$2:$B$104,"Fev/2026",Lancamentos!$D$2:$D$104,"Consultoria") -> 0 | D11: =SUMIFS(Lancamentos!$H$2:$H$104,Lancamentos!$B$2:$B$104,"Mar/2026",Lancamentos!$D$2:$D$104,"Consultoria") -> 48000 | E11: =SUM(B11:D11) -> 48000 | F11: =E11/$E$30 -> 0.057952117
A12: Contabilidade | B12: =SUMIFS(Lancamentos!$H$2:$H$104,Lancamentos!$B$2:$B$104,"Jan/2026",Lancamentos!$D$2:$D$104,"Contabilidade") -> 2800 | C12: =SUMIFS(Lancamentos!$H$2:$H$104,Lancamentos!$B$2:$B$104,"Fev/2026",Lancamentos!$D$2:$D$104,"Contabilidade") -> 2800 | D12: =SUMIFS(Lancamentos!$H$2:$H$104,Lancamentos!$B$2:$B$104,"Mar/2026",Lancamentos!$D$2:$D$104,"Contabilidade") -> 2800 | E12: =SUM(B12:D12) -> 8400 | F12: =E12/$E$30 -> 0.01014162
A13: Despesas Bancárias | B13: =SUMIFS(Lancamentos!$H$2:$H$104,Lancamentos!$B$2:$B$104,"Jan/2026",Lancamentos!$D$2:$D$104,"Despesas Bancárias") -> 480 | C13: =SUMIFS(Lancamentos!$H$2:$H$104,Lancamentos!$B$2:$B$104,"Fev/2026",Lancamentos!$D$2:$D$104,"Despesas Bancárias") -> 510 | D13: =SUMIFS(Lancamentos!$H$2:$H$104,Lancamentos!$B$2:$B$104,"Mar/2026",Lancamentos!$D$2:$D$104,"Despesas Bancárias") -> 3950 | E13: =SUM(B13:D13) -> 4940 | F13: =E13/$E$30 -> 0.0059642387
A14: Encargos Sociais (INSS/FGTS) | B14: =SUMIFS(Lancamentos!$H$2:$H$104,Lancamentos!$B$2:$B$104,"Jan/2026",Lancamentos!$D$2:$D$104,"Encargos Sociais (INSS/FGTS)") -> 12200 | C14: =SUMIFS(Lancamentos!$H$2:$H$104,Lancamentos!$B$2:$B$104,"Fev/2026",Lancamentos!$D$2:$D$104,"Encargos Sociais (INSS/FGTS)") -> 12200 | D14: =SUMIFS(Lancamentos!$H$2:$H$104,Lancamentos!$B$2:$B$104,"Mar/2026",Lancamentos!$D$2:$D$104,"Encargos Sociais (INSS/FGTS)") -> 12200 | E14: =SUM(B14:D14) -> 36600 | F14: =E14/$E$30 -> 0.044188489
A15: Energia Elétrica | B15: =SUMIFS(Lancamentos!$H$2:$H$104,Lancamentos!$B$2:$B$104,"Jan/2026",Lancamentos!$D$2:$D$104,"Energia Elétrica") -> 5200 | C15: =SUMIFS(Lancamentos!$H$2:$H$104,Lancamentos!$B$2:$B$104,"Fev/2026",Lancamentos!$D$2:$D$104,"Energia Elétrica") -> 5600 | D15: =SUMIFS(Lancamentos!$H$2:$H$104,Lancamentos!$B$2:$B$104,"Mar/2026",Lancamentos!$D$2:$D$104,"Energia Elétrica") -> 6100 | E15: =SUM(B15:D15) -> 16900 | F15: =E15/$E$30 -> 0.020403975
A16: Folha de Pagamento | B16: =SUMIFS(Lancamentos!$H$2:$H$104,Lancamentos!$B$2:$B$104,"Jan/2026",Lancamentos!$D$2:$D$104,"Folha de Pagamento") -> 36500 | C16: =SUMIFS(Lancamentos!$H$2:$H$104,Lancamentos!$B$2:$B$104,"Fev/2026",Lancamentos!$D$2:$D$104,"Folha de Pagamento") -> 36500 | D16: =SUMIFS(Lancamentos!$H$2:$H$104,Lancamentos!$B$2:$B$104,"Mar/2026",Lancamentos!$D$2:$D$104,"Folha de Pagamento") -> 36500 | E16: =SUM(B16:D16) -> 109500 | F16: =E16/$E$30 -> 0.13220327
A17: Frete e Logística | B17: =SUMIFS(Lancamentos!$H$2:$H$104,Lancamentos!$B$2:$B$104,"Jan/2026",Lancamentos!$D$2:$D$104,"Frete e Logística") -> 6100 | C17: =SUMIFS(Lancamentos!$H$2:$H$104,Lancamentos!$B$2:$B$104,"Fev/2026",Lancamentos!$D$2:$D$104,"Frete e Logística") -> 9300 | D17: =SUMIFS(Lancamentos!$H$2:$H$104,Lancamentos!$B$2:$B$104,"Mar/2026",Lancamentos!$D$2:$D$104,"Frete e Logística") -> 13200 | E17: =SUM(B17:D17) -> 28600 | F17: =E17/$E$30 -> 0.034529803
A18: Impostos - Simples Nacional (DAS) | B18: =SUMIFS(Lancamentos!$H$2:$H$104,Lancamentos!$B$2:$B$104,"Jan/2026",Lancamentos!$D$2:$D$104,"Impostos - Simples Nacional (DAS)") -> 16000 | C18: =SUMIFS(Lancamentos!$H$2:$H$104,Lancamentos!$B$2:$B$104,"Fev/2026",Lancamentos!$D$2:$D$104,"Impostos - Simples Nacional (DAS)") -> 15300 | D18: =SUMIFS(Lancamentos!$H$2:$H$104,Lancamentos!$B$2:$B$104,"Mar/2026",Lancamentos!$D$2:$D$104,"Impostos - Simples Nacional (DAS)") -> 14500 | E18: =SUM(B18:D18) -> 45800 | F18: =E18/$E$30 -> 0.055295978
A19: Limpeza e Conservação | B19: =SUMIFS(Lancamentos!$H$2:$H$104,Lancamentos!$B$2:$B$104,"Jan/2026",Lancamentos!$D$2:$D$104,"Limpeza e Conservação") -> 1600 | C19: =SUMIFS(Lancamentos!$H$2:$H$104,Lancamentos!$B$2:$B$104,"Fev/2026",Lancamentos!$D$2:$D$104,"Limpeza e Conservação") -> 1600 | D19: =SUMIFS(Lancamentos!$H$2:$H$104,Lancamentos!$B$2:$B$104,"Mar/2026",Lancamentos!$D$2:$D$104,"Limpeza e Conservação") -> 1600 | E19: =SUM(B19:D19) -> 4800 | F19: =E19/$E$30 -> 0.0057952117
A20: Manutenção e Reparos | B20: =SUMIFS(Lancamentos!$H$2:$H$104,Lancamentos!$B$2:$B$104,"Jan/2026",Lancamentos!$D$2:$D$104,"Manutenção e Reparos") -> 1900 | C20: =SUMIFS(Lancamentos!$H$2:$H$104,Lancamentos!$B$2:$B$104,"Fev/2026",Lancamentos!$D$2:$D$104,"Manutenção e Reparos") -> 2100 | D20: =SUMIFS(Lancamentos!$H$2:$H$104,Lancamentos!$B$2:$B$104,"Mar/2026",Lancamentos!$D$2:$D$104,"Manutenção e Reparos") -> 1800 | E20: =SUM(B20:D20) -> 5800 | F20: =E20/$E$30 -> 0.0070025475
A21: Marketing e Publicidade | B21: =SUMIFS(Lancamentos!$H$2:$H$104,Lancamentos!$B$2:$B$104,"Jan/2026",Lancamentos!$D$2:$D$104,"Marketing e Publicidade") -> 8200 | C21: =SUMIFS(Lancamentos!$H$2:$H$104,Lancamentos!$B$2:$B$104,"Fev/2026",Lancamentos!$D$2:$D$104,"Marketing e Publicidade") -> 7600 | D21: =SUMIFS(Lancamentos!$H$2:$H$104,Lancamentos!$B$2:$B$104,"Mar/2026",Lancamentos!$D$2:$D$104,"Marketing e Publicidade") -> 31500 | E21: =SUM(B21:D21) -> 47300 | F21: =E21/$E$30 -> 0.057106982
A22: Material de Embalagem | B22: =SUMIFS(Lancamentos!$H$2:$H$104,Lancamentos!$B$2:$B$104,"Jan/2026",Lancamentos!$D$2:$D$104,"Material de Embalagem") -> 2200 | C22: =SUMIFS(Lancamentos!$H$2:$H$104,Lancamentos!$B$2:$B$104,"Fev/2026",Lancamentos!$D$2:$D$104,"Material de Embalagem") -> 2350 | D22: =SUMIFS(Lancamentos!$H$2:$H$104,Lancamentos!$B$2:$B$104,"Mar/2026",Lancamentos!$D$2:$D$104,"Material de Embalagem") -> 2500 | E22: =SUM(B22:D22) -> 7050 | F22: =E22/$E$30 -> 0.0085117172
A23: Material de Escritório | B23: =SUMIFS(Lancamentos!$H$2:$H$104,Lancamentos!$B$2:$B$104,"Jan/2026",Lancamentos!$D$2:$D$104,"Material de Escritório") -> 720 | C23: =SUMIFS(Lancamentos!$H$2:$H$104,Lancamentos!$B$2:$B$104,"Fev/2026",Lancamentos!$D$2:$D$104,"Material de Escritório") -> 14200 | D23: =SUMIFS(Lancamentos!$H$2:$H$104,Lancamentos!$B$2:$B$104,"Mar/2026",Lancamentos!$D$2:$D$104,"Material de Escritório") -> 680 | E23: =SUM(B23:D23) -> 15600 | F23: =E23/$E$30 -> 0.018834438
A24: Mercadorias para Revenda (CMV) | B24: =SUMIFS(Lancamentos!$H$2:$H$104,Lancamentos!$B$2:$B$104,"Jan/2026",Lancamentos!$D$2:$D$104,"Mercadorias para Revenda (CMV)") -> 125000 | C24: =SUMIFS(Lancamentos!$H$2:$H$104,Lancamentos!$B$2:$B$104,"Fev/2026",Lancamentos!$D$2:$D$104,"Mercadorias para Revenda (CMV)") -> 119000 | D24: =SUMIFS(Lancamentos!$H$2:$H$104,Lancamentos!$B$2:$B$104,"Mar/2026",Lancamentos!$D$2:$D$104,"Mercadorias para Revenda (CMV)") -> 116000 | E24: =SUM(B24:D24) -> 360000 | F24: =E24/$E$30 -> 0.43464088
A25: Seguros | B25: =SUMIFS(Lancamentos!$H$2:$H$104,Lancamentos!$B$2:$B$104,"Jan/2026",Lancamentos!$D$2:$D$104,"Seguros") -> 1350 | C25: =SUMIFS(Lancamentos!$H$2:$H$104,Lancamentos!$B$2:$B$104,"Fev/2026",Lancamentos!$D$2:$D$104,"Seguros") -> 1350 | D25: =SUMIFS(Lancamentos!$H$2:$H$104,Lancamentos!$B$2:$B$104,"Mar/2026",Lancamentos!$D$2:$D$104,"Seguros") -> 1350 | E25: =SUM(B25:D25) -> 4050 | F25: =E25/$E$30 -> 0.0048897099
A26: Software e Assinaturas | B26: =SUMIFS(Lancamentos!$H$2:$H$104,Lancamentos!$B$2:$B$104,"Jan/2026",Lancamentos!$D$2:$D$104,"Software e Assinaturas") -> 1240 | C26: =SUMIFS(Lancamentos!$H$2:$H$104,Lancamentos!$B$2:$B$104,"Fev/2026",Lancamentos!$D$2:$D$104,"Software e Assinaturas") -> 1240 | D26: =SUMIFS(Lancamentos!$H$2:$H$104,Lancamentos!$B$2:$B$104,"Mar/2026",Lancamentos!$D$2:$D$104,"Software e Assinaturas") -> 1240 | E26: =SUM(B26:D26) -> 3720 | F26: =E26/$E$30 -> 0.0044912891
A27: Taxas de Cartão/Maquininha | B27: =SUMIFS(Lancamentos!$H$2:$H$104,Lancamentos!$B$2:$B$104,"Jan/2026",Lancamentos!$D$2:$D$104,"Taxas de Cartão/Maquininha") -> 6700 | C27: =SUMIFS(Lancamentos!$H$2:$H$104,Lancamentos!$B$2:$B$104,"Fev/2026",Lancamentos!$D$2:$D$104,"Taxas de Cartão/Maquininha") -> 6650 | D27: =SUMIFS(Lancamentos!$H$2:$H$104,Lancamentos!$B$2:$B$104,"Mar/2026",Lancamentos!$D$2:$D$104,"Taxas de Cartão/Maquininha") -> 6500 | E27: =SUM(B27:D27) -> 19850 | F27: =E27/$E$30 -> 0.023965615
A28: Telefone e Internet | B28: =SUMIFS(Lancamentos!$H$2:$H$104,Lancamentos!$B$2:$B$104,"Jan/2026",Lancamentos!$D$2:$D$104,"Telefone e Internet") -> 1450 | C28: =SUMIFS(Lancamentos!$H$2:$H$104,Lancamentos!$B$2:$B$104,"Fev/2026",Lancamentos!$D$2:$D$104,"Telefone e Internet") -> 1450 | D28: =SUMIFS(Lancamentos!$H$2:$H$104,Lancamentos!$B$2:$B$104,"Mar/2026",Lancamentos!$D$2:$D$104,"Telefone e Internet") -> 1450 | E28: =SUM(B28:D28) -> 4350 | F28: =E28/$E$30 -> 0.0052519106
A29: Água e Esgoto | B29: =SUMIFS(Lancamentos!$H$2:$H$104,Lancamentos!$B$2:$B$104,"Jan/2026",Lancamentos!$D$2:$D$104,"Água e Esgoto") -> 980 | C29: =SUMIFS(Lancamentos!$H$2:$H$104,Lancamentos!$B$2:$B$104,"Fev/2026",Lancamentos!$D$2:$D$104,"Água e Esgoto") -> 1020 | D29: =SUMIFS(Lancamentos!$H$2:$H$104,Lancamentos!$B$2:$B$104,"Mar/2026",Lancamentos!$D$2:$D$104,"Água e Esgoto") -> 1010 | E29: =SUM(B29:D29) -> 3010 | F29: =E29/$E$30 -> 0.0036340807
A30: Total Despesas | B30: =SUM(B10:B29) -> 248620 | C30: =SUM(C10:C29) -> 258770 | D30: =SUM(D10:D29) -> 320880 | E30: =SUM(E10:E29) -> 828270 | F30: =E30/$E$30 -> 1
A32: RESULTADO (Receitas − Despesas) | B32: =B7-B30 -> 19380 | C32: =C7-C30 -> -3770 | D32: =D7-D30 -> -79880 | E32: =E7-E30 -> -64270
A33: Margem líquida | B33: =IF(B7=0,0,B32/B7) -> 0.072313433 | C33: =IF(C7=0,0,C32/C7) -> -0.014784314 | D33: =IF(D7=0,0,D32/D7) -> -0.33145228 | E33: =IF(E7=0,0,E32/E7) -> -0.084123037

Sheet Gabarito (Instrutor)
B1: GABARITO DO INSTRUTOR
B2: O que foi plantado nos dados (apague esta aba antes de distribuir, se quiser).
B4: Eixo | C4: Detalhe | D4: Descrição
B5: ANOMALIA | C5: [Duplicata] Fornecedor 'Alfa Distribuidora Ltda', NF 04532, R$ 12.480,00 lançada DUAS vezes em Fev (11/02 e 13/02). Pagamento em duplicidade.
B6: ANOMALIA | C6: [Pico inexplicado] 'Material de Escritório' salta de ~R$ 700/mês para R$ 14.200 em Fev (compra avulsa de móveis/equip. lançada na categoria errada).
B7: ANOMALIA | C7: [Pico inexplicado] 'Marketing' salta de ~R$ 8.000 para R$ 31.500 em Mar — R$ 24.000 de 'Campanha Influencer' avulsa.
B8: ANOMALIA | C8: [Tarifa atípica] 'Despesas Bancárias' tem 'Tarifa não identificada' de R$ 3.500 em Mar (vs ~R$ 500/mês).
B9: ANOMALIA | C9: [Gasto avulso alto] 'Consultoria' de R$ 48.000 em Mar, fornecedor avulso, valor redondo, sem recorrência.
B10: TENDÊNCIA | C10: [Receita em queda] Faturamento cai 3 meses seguidos: 268k → 255k → 241k (−10% no trimestre).
B11: TENDÊNCIA | C11: [Frete subindo] 'Frete e Logística' sobe: 6,1k → 9,3k → 13,2k (+116%) — pressiona a margem.
B12: TENDÊNCIA | C12: [Energia subindo] 'Energia Elétrica' sobe gradualmente (5,2k → 6,1k).
B13: ALERTA | C13: [Margem comprimida] Receita caindo + custos avulsos altos em Mar derrubam o resultado do mês — verifique a margem líquida na aba Resumo.
B14: TOP DESPESAS | C14: [Esperado] 1) Mercadorias/CMV 2) Folha 3) Aluguel 4) Frete 5) Marketing ou Encargos (varia por mês).
